LICENSE.txt
MANIFEST.in
README.md
setup.py
cbench/__init__.py
cbench/__main__.py
cbench/client.py
cbench/comm.py
cbench/comm_min.py
cbench/config.py
cbench/graph.py
cbench/main.py
cbench/obj.py
cbench/setup.py
cbench/solution.py
cbench.egg-info/PKG-INFO
cbench.egg-info/SOURCES.txt
cbench.egg-info/dependency_links.txt
cbench.egg-info/entry_points.txt
cbench.egg-info/not-zip-safe
cbench.egg-info/requires.txt
cbench.egg-info/top_level.txt
cbench/static/favicon.ico