Metadata-Version: 2.1
Name: cbench
Version: 1.2.11
Summary: A cross-platform client to perform collaborative and reproducible benchmarking, optimization and co-design of software and hardware for emerging workloads (AI, ML, quantum, IoT) via the open cKnowledge.io portal
Home-page: https://cKnowledge.io
Author: Grigori Fursin
Author-email: Grigori.Fursin@cTuning.org
License: Apache Software License (Apache 2.0)
Keywords: reproducible benchmarking,customizable benchmarking,portable workflows,reusable computational components,reproducibility,collaborative experiments,automation,optimization,co-design,collective knowledge
Platform: UNKNOWN
Classifier: Development Status :: 5 - Production/Stable
Classifier: Programming Language :: Python :: 2.7
Classifier: Programming Language :: Python :: 3
Classifier: Intended Audience :: Developers
Classifier: Intended Audience :: Education
Classifier: Intended Audience :: End Users/Desktop
Classifier: Intended Audience :: Information Technology
Classifier: Intended Audience :: Science/Research
Classifier: Environment :: Console
Classifier: Environment :: Plugins
Classifier: Environment :: Web Environment
Classifier: License :: OSI Approved :: BSD License
Classifier: Operating System :: OS Independent
Classifier: Topic :: Scientific/Engineering
Classifier: Topic :: Software Development
Classifier: Topic :: System
Classifier: Topic :: System :: Benchmark
Classifier: Topic :: Education
Classifier: Topic :: Utilities
Requires-Python: >=2.7
